odoo/addons/pos_order_mgmt/README.rst
odoo/addons/pos_order_mgmt/__init__.py
odoo/addons/pos_order_mgmt/__manifest__.py
odoo/addons/pos_order_mgmt/i18n/es.po
odoo/addons/pos_order_mgmt/i18n/pos_order_mgmt.pot
odoo/addons/pos_order_mgmt/models/__init__.py
odoo/addons/pos_order_mgmt/models/pos_config.py
odoo/addons/pos_order_mgmt/models/pos_order.py
odoo/addons/pos_order_mgmt/readme/CONFIGURE.rst
odoo/addons/pos_order_mgmt/readme/CONTRIBUTORS.rst
odoo/addons/pos_order_mgmt/readme/DESCRIPTION.rst
odoo/addons/pos_order_mgmt/readme/ROADMAP.rst
odoo/addons/pos_order_mgmt/readme/USAGE.rst
odoo/addons/pos_order_mgmt/static/description/icon.png
odoo/addons/pos_order_mgmt/static/description/index.html
odoo/addons/pos_order_mgmt/static/description/order-mgmt-icon.png
odoo/addons/pos_order_mgmt/static/description/order-mgmt-list.png
odoo/addons/pos_order_mgmt/static/src/css/pos.css
odoo/addons/pos_order_mgmt/static/src/js/models.js
odoo/addons/pos_order_mgmt/static/src/js/widgets.js
odoo/addons/pos_order_mgmt/static/src/xml/pos.xml
odoo/addons/pos_order_mgmt/views/assets.xml
odoo/addons/pos_order_mgmt/views/view_pos_config.xml
odoo11_addon_pos_order_mgmt-11.0.1.0.4.dist-info/METADATA
odoo11_addon_pos_order_mgmt-11.0.1.0.4.dist-info/WHEEL
odoo11_addon_pos_order_mgmt-11.0.1.0.4.dist-info/top_level.txt
odoo11_addon_pos_order_mgmt-11.0.1.0.4.dist-info/RECORD
